{"config":{"output_file":null,"full_docs":false,"pub_only":false,"reachable_only":false,"distro_crate":false,"signatures":false,"borrow_data":false},"version":"0.19.1","compilation":{"directory":"/Users/qinjianquan/rust-projects/chat/client","program":"/Users/qinjianquan/.rustup/toolchains/nightly-x86_64-apple-darwin/bin/rls","arguments":[],"output":"/Users/qinjianquan/rust-projects/chat/client/target/rls/debug/deps/libclient-03124e6ba7415983.rmeta"},"prelude":{"crate_id":{"name":"client","disambiguator":[11309270699967838810,0]},"crate_root":"src","external_crates":[{"file_name":"/Users/qinjianquan/rust-projects/chat/client/src/main.rs","num":1,"id":{"name":"std","disambiguator":[12559688530690724281,0]}},{"file_name":"/Users/qinjianquan/rust-projects/chat/client/src/main.rs","num":2,"id":{"name":"core","disambiguator":[174151012323878463,0]}},{"file_name":"/Users/qinjianquan/rust-projects/chat/client/src/main.rs","num":3,"id":{"name":"compiler_builtins","disambiguator":[10235651058269579681,0]}},{"file_name":"/Users/qinjianquan/rust-projects/chat/client/src/main.rs","num":4,"id":{"name":"rustc_std_workspace_core","disambiguator":[12116087461466967610,0]}},{"file_name":"/Users/qinjianquan/rust-projects/chat/client/src/main.rs","num":5,"id":{"name":"alloc","disambiguator":[483691506014662373,0]}},{"file_name":"/Users/qinjianquan/rust-projects/chat/client/src/main.rs","num":6,"id":{"name":"libc","disambiguator":[15265217745217534414,0]}},{"file_name":"/Users/qinjianquan/rust-projects/chat/client/src/main.rs","num":7,"id":{"name":"unwind","disambiguator":[10524025089107222904,0]}},{"file_name":"/Users/qinjianquan/rust-projects/chat/client/src/main.rs","num":8,"id":{"name":"cfg_if","disambiguator":[380231209694308790,0]}},{"file_name":"/Users/qinjianquan/rust-projects/chat/client/src/main.rs","num":9,"id":{"name":"miniz_oxide","disambiguator":[6799936204780222302,0]}},{"file_name":"/Users/qinjianquan/rust-projects/chat/client/src/main.rs","num":10,"id":{"name":"rustc_std_workspace_alloc","disambiguator":[12259298289434686045,0]}},{"file_name":"/Users/qinjianquan/rust-projects/chat/client/src/main.rs","num":11,"id":{"name":"adler","disambiguator":[12106170270815753816,0]}},{"file_name":"/Users/qinjianquan/rust-projects/chat/client/src/main.rs","num":12,"id":{"name":"hashbrown","disambiguator":[4360076971198232690,0]}},{"file_name":"/Users/qinjianquan/rust-projects/chat/client/src/main.rs","num":13,"id":{"name":"std_detect","disambiguator":[9958527644082841145,0]}},{"file_name":"/Users/qinjianquan/rust-projects/chat/client/src/main.rs","num":14,"id":{"name":"rustc_demangle","disambiguator":[17047570305521200150,0]}},{"file_name":"/Users/qinjianquan/rust-projects/chat/client/src/main.rs","num":15,"id":{"name":"addr2line","disambiguator":[9299774619811639326,0]}},{"file_name":"/Users/qinjianquan/rust-projects/chat/client/src/main.rs","num":16,"id":{"name":"gimli","disambiguator":[7916745300923032827,0]}},{"file_name":"/Users/qinjianquan/rust-projects/chat/client/src/main.rs","num":17,"id":{"name":"object","disambiguator":[12567887698174358418,0]}},{"file_name":"/Users/qinjianquan/rust-projects/chat/client/src/main.rs","num":18,"id":{"name":"memchr","disambiguator":[13522633749795580280,0]}},{"file_name":"/Users/qinjianquan/rust-projects/chat/client/src/main.rs","num":19,"id":{"name":"panic_unwind","disambiguator":[3127363703815277095,0]}}],"span":{"file_name":"src/main.rs","byte_start":0,"byte_end":2052,"line_start":1,"line_end":66,"column_start":1,"column_end":2}},"imports":[{"kind":"Use","ref_id":{"krate":1,"index":3261},"span":{"file_name":"src/main.rs","byte_start":9,"byte_end":11,"line_start":1,"line_end":1,"column_start":10,"column_end":12},"alias_span":null,"name":"io","value":"","parent":{"krate":0,"index":0}},{"kind":"Use","ref_id":{"krate":1,"index":10479},"span":{"file_name":"src/main.rs","byte_start":20,"byte_end":29,"line_start":1,"line_end":1,"column_start":21,"column_end":30},"alias_span":null,"name":"ErrorKind","value":"","parent":{"krate":0,"index":0}},{"kind":"Use","ref_id":{"krate":1,"index":4509},"span":{"file_name":"src/main.rs","byte_start":31,"byte_end":35,"line_start":1,"line_end":1,"column_start":32,"column_end":36},"alias_span":null,"name":"Read","value":"","parent":{"krate":0,"index":0}},{"kind":"Use","ref_id":{"krate":1,"index":4566},"span":{"file_name":"src/main.rs","byte_start":37,"byte_end":42,"line_start":1,"line_end":1,"column_start":38,"column_end":43},"alias_span":null,"name":"Write","value":"","parent":{"krate":0,"index":0}},{"kind":"Use","ref_id":{"krate":1,"index":5251},"span":{"file_name":"src/main.rs","byte_start":59,"byte_end":68,"line_start":2,"line_end":2,"column_start":15,"column_end":24},"alias_span":null,"name":"TcpStream","value":"","parent":{"krate":0,"index":0}},{"kind":"Use","ref_id":{"krate":1,"index":7483},"span":{"file_name":"src/main.rs","byte_start":85,"byte_end":89,"line_start":3,"line_end":3,"column_start":16,"column_end":20},"alias_span":null,"name":"mpsc","value":"","parent":{"krate":0,"index":0}},{"kind":"Use","ref_id":{"krate":1,"index":11616},"span":{"file_name":"src/main.rs","byte_start":98,"byte_end":110,"line_start":3,"line_end":3,"column_start":29,"column_end":41},"alias_span":null,"name":"TryRecvError","value":"","parent":{"krate":0,"index":0}},{"kind":"Use","ref_id":{"krate":1,"index":610},"span":{"file_name":"src/main.rs","byte_start":122,"byte_end":128,"line_start":4,"line_end":4,"column_start":10,"column_end":16},"alias_span":null,"name":"thread","value":"","parent":{"krate":0,"index":0}},{"kind":"Use","ref_id":{"krate":2,"index":49814},"span":{"file_name":"src/main.rs","byte_start":145,"byte_end":153,"line_start":5,"line_end":5,"column_start":16,"column_end":24},"alias_span":null,"name":"Duration","value":"","parent":{"krate":0,"index":0}}],"defs":[{"kind":"Mod","id":{"krate":0,"index":0},"span":{"file_name":"src/main.rs","byte_start":0,"byte_end":2052,"line_start":1,"line_end":66,"column_start":1,"column_end":2},"name":"","qualname":"::","value":"src/main.rs","parent":null,"children":[{"krate":0,"index":1},{"krate":0,"index":2},{"krate":0,"index":3},{"krate":0,"index":4},{"krate":0,"index":7},{"krate":0,"index":10},{"krate":0,"index":13},{"krate":0,"index":16},{"krate":0,"index":19},{"krate":0,"index":20},{"krate":0,"index":23},{"krate":0,"index":26},{"krate":0,"index":29},{"krate":0,"index":32},{"krate":0,"index":33},{"krate":0,"index":34}],"decl_id":null,"docs":"","sig":null,"attributes":[]},{"kind":"Const","id":{"krate":0,"index":32},"span":{"file_name":"src/main.rs","byte_start":162,"byte_end":167,"line_start":7,"line_end":7,"column_start":7,"column_end":12},"name":"LOCAL","qualname":"::LOCAL","value":"&str","parent":null,"children":[],"decl_id":null,"docs":"","sig":null,"attributes":[]},{"kind":"Const","id":{"krate":0,"index":33},"span":{"file_name":"src/main.rs","byte_start":218,"byte_end":226,"line_start":8,"line_end":8,"column_start":7,"column_end":15},"name":"MSG_SIZE","qualname":"::MSG_SIZE","value":"usize","parent":null,"children":[],"decl_id":null,"docs":"","sig":null,"attributes":[]},{"kind":"Function","id":{"krate":0,"index":34},"span":{"file_name":"src/main.rs","byte_start":277,"byte_end":281,"line_start":10,"line_end":10,"column_start":4,"column_end":8},"name":"main","qualname":"::main","value":"fn main()","parent":null,"children":[],"decl_id":null,"docs":"","sig":null,"attributes":[]},{"kind":"Local","id":{"krate":0,"index":2952790050},"span":{"file_name":"src/main.rs","byte_start":329,"byte_end":335,"line_start":12,"line_end":12,"column_start":13,"column_end":19},"name":"client","qualname":"client$HirId { owner: DefId(0:34 ~ client[9cf2]::main), local_id: 13 }","value":"std::net::TcpStream","parent":null,"children":[],"decl_id":null,"docs":"","sig":null,"attributes":[]},{"kind":"Local","id":{"krate":0,"index":4160749602},"span":{"file_name":"src/main.rs","byte_start":555,"byte_end":557,"line_start":20,"line_end":20,"column_start":10,"column_end":12},"name":"tx","qualname":"tx$HirId { owner: DefId(0:34 ~ client[9cf2]::main), local_id: 31 }","value":"std::sync::mpsc::Sender<std::string::String>","parent":null,"children":[],"decl_id":null,"docs":"","sig":null,"attributes":[]},{"kind":"Local","id":{"krate":0,"index":67108898},"span":{"file_name":"src/main.rs","byte_start":559,"byte_end":561,"line_start":20,"line_end":20,"column_start":14,"column_end":16},"name":"rx","qualname":"rx$HirId { owner: DefId(0:34 ~ client[9cf2]::main), local_id: 32 }","value":"std::sync::mpsc::Receiver<std::string::String>","parent":null,"children":[],"decl_id":null,"docs":"","sig":null,"attributes":[]},{"kind":"Local","id":{"krate":0,"index":4093640738},"span":{"file_name":"src/main.rs","byte_start":712,"byte_end":716,"line_start":25,"line_end":25,"column_start":17,"column_end":21},"name":"buff","qualname":"buff$HirId { owner: DefId(0:34 ~ client[9cf2]::main), local_id: 47 }","value":"std::vec::Vec<u8>","parent":null,"children":[],"decl_id":null,"docs":"","sig":null,"attributes":[]},{"kind":"Local","id":{"krate":0,"index":2315255842},"span":{"file_name":"src/main.rs","byte_start":878,"byte_end":881,"line_start":30,"line_end":30,"column_start":21,"column_end":24},"name":"msg","qualname":"msg$HirId { owner: DefId(0:34 ~ client[9cf2]::main), local_id: 81 }","value":"std::vec::Vec<u8>","parent":null,"children":[],"decl_id":null,"docs":"","sig":null,"attributes":[]},{"kind":"Local","id":{"krate":0,"index":1644167202},"span":{"file_name":"src/main.rs","byte_start":914,"byte_end":915,"line_start":30,"line_end":30,"column_start":57,"column_end":58},"name":"x","qualname":"$HirId { owner: DefId(0:34 ~ client[9cf2]::main), local_id: 77 }::x","value":"u8","parent":null,"children":[],"decl_id":null,"docs":"","sig":null,"attributes":[]},{"kind":"Local","id":{"krate":0,"index":3992977442},"span":{"file_name":"src/main.rs","byte_start":1059,"byte_end":1062,"line_start":34,"line_end":34,"column_start":21,"column_end":24},"name":"err","qualname":"err$HirId { owner: DefId(0:34 ~ client[9cf2]::main), local_id: 119 }","value":"&std::io::Error","parent":null,"children":[],"decl_id":null,"docs":"","sig":null,"attributes":[]},{"kind":"Local","id":{"krate":0,"index":2499805218},"span":{"file_name":"src/main.rs","byte_start":1290,"byte_end":1293,"line_start":42,"line_end":42,"column_start":16,"column_end":19},"name":"msg","qualname":"msg$HirId { owner: DefId(0:34 ~ client[9cf2]::main), local_id: 169 }","value":"std::string::String","parent":null,"children":[],"decl_id":null,"docs":"","sig":null,"attributes":[]},{"kind":"Local","id":{"krate":0,"index":754974754},"span":{"file_name":"src/main.rs","byte_start":1324,"byte_end":1328,"line_start":43,"line_end":43,"column_start":25,"column_end":29},"name":"buff","qualname":"buff$HirId { owner: DefId(0:34 ~ client[9cf2]::main), local_id: 180 }","value":"std::vec::Vec<u8>","parent":null,"children":[],"decl_id":null,"docs":"","sig":null,"attributes":[]},{"kind":"Local","id":{"krate":0,"index":343932962},"span":{"file_name":"src/main.rs","byte_start":1769,"byte_end":1773,"line_start":56,"line_end":56,"column_start":17,"column_end":21},"name":"buff","qualname":"buff$HirId { owner: DefId(0:34 ~ client[9cf2]::main), local_id: 296 }","value":"std::string::String","parent":null,"children":[],"decl_id":null,"docs":"","sig":null,"attributes":[]},{"kind":"Local","id":{"krate":0,"index":2088763426},"span":{"file_name":"src/main.rs","byte_start":1907,"byte_end":1910,"line_start":60,"line_end":60,"column_start":13,"column_end":16},"name":"msg","qualname":"msg$HirId { owner: DefId(0:34 ~ client[9cf2]::main), local_id: 318 }","value":"std::string::String","parent":null,"children":[],"decl_id":null,"docs":"","sig":null,"attributes":[]}],"impls":[],"refs":[{"kind":"Mod","span":{"file_name":"src/main.rs","byte_start":4,"byte_end":7,"line_start":1,"line_end":1,"column_start":5,"column_end":8},"ref_id":{"krate":1,"index":3261}},{"kind":"Type","span":{"file_name":"src/main.rs","byte_start":4,"byte_end":7,"line_start":1,"line_end":1,"column_start":5,"column_end":8},"ref_id":{"krate":1,"index":10479}},{"kind":"Type","span":{"file_name":"src/main.rs","byte_start":9,"byte_end":11,"line_start":1,"line_end":1,"column_start":10,"column_end":12},"ref_id":{"krate":1,"index":10479}},{"kind":"Type","span":{"file_name":"src/main.rs","byte_start":4,"byte_end":7,"line_start":1,"line_end":1,"column_start":5,"column_end":8},"ref_id":{"krate":1,"index":4509}},{"kind":"Type","span":{"file_name":"src/main.rs","byte_start":9,"byte_end":11,"line_start":1,"line_end":1,"column_start":10,"column_end":12},"ref_id":{"krate":1,"index":4509}},{"kind":"Type","span":{"file_name":"src/main.rs","byte_start":4,"byte_end":7,"line_start":1,"line_end":1,"column_start":5,"column_end":8},"ref_id":{"krate":1,"index":4566}},{"kind":"Type","span":{"file_name":"src/main.rs","byte_start":9,"byte_end":11,"line_start":1,"line_end":1,"column_start":10,"column_end":12},"ref_id":{"krate":1,"index":4566}},{"kind":"Mod","span":{"file_name":"src/main.rs","byte_start":49,"byte_end":52,"line_start":2,"line_end":2,"column_start":5,"column_end":8},"ref_id":{"krate":1,"index":0}},{"kind":"Mod","span":{"file_name":"src/main.rs","byte_start":54,"byte_end":57,"line_start":2,"line_end":2,"column_start":10,"column_end":13},"ref_id":{"krate":1,"index":4674}},{"kind":"Mod","span":{"file_name":"src/main.rs","byte_start":74,"byte_end":77,"line_start":3,"line_end":3,"column_start":5,"column_end":8},"ref_id":{"krate":1,"index":7483}},{"kind":"Mod","span":{"file_name":"src/main.rs","byte_start":79,"byte_end":83,"line_start":3,"line_end":3,"column_start":10,"column_end":14},"ref_id":{"krate":1,"index":7483}},{"kind":"Type","span":{"file_name":"src/main.rs","byte_start":74,"byte_end":77,"line_start":3,"line_end":3,"column_start":5,"column_end":8},"ref_id":{"krate":1,"index":11616}},{"kind":"Type","span":{"file_name":"src/main.rs","byte_start":79,"byte_end":83,"line_start":3,"line_end":3,"column_start":10,"column_end":14},"ref_id":{"krate":1,"index":11616}},{"kind":"Type","span":{"file_name":"src/main.rs","byte_start":85,"byte_end":89,"line_start":3,"line_end":3,"column_start":16,"column_end":20},"ref_id":{"krate":1,"index":11616}},{"kind":"Mod","span":{"file_name":"src/main.rs","byte_start":117,"byte_end":120,"line_start":4,"line_end":4,"column_start":5,"column_end":8},"ref_id":{"krate":1,"index":0}},{"kind":"Mod","span":{"file_name":"src/main.rs","byte_start":134,"byte_end":137,"line_start":5,"line_end":5,"column_start":5,"column_end":8},"ref_id":{"krate":1,"index":0}},{"kind":"Mod","span":{"file_name":"src/main.rs","byte_start":139,"byte_end":143,"line_start":5,"line_end":5,"column_start":10,"column_end":14},"ref_id":{"krate":1,"index":8679}},{"kind":"Function","span":{"file_name":"src/main.rs","byte_start":364,"byte_end":370,"line_start":12,"line_end":12,"column_start":48,"column_end":54},"ref_id":{"krate":2,"index":9364}},{"kind":"Function","span":{"file_name":"src/main.rs","byte_start":349,"byte_end":356,"line_start":12,"line_end":12,"column_start":33,"column_end":40},"ref_id":{"krate":1,"index":5258}},{"kind":"Type","span":{"file_name":"src/main.rs","byte_start":338,"byte_end":347,"line_start":12,"line_end":12,"column_start":22,"column_end":31},"ref_id":{"krate":1,"index":5251}},{"kind":"Variable","span":{"file_name":"src/main.rs","byte_start":357,"byte_end":362,"line_start":12,"line_end":12,"column_start":41,"column_end":46},"ref_id":{"krate":0,"index":32}},{"kind":"Function","span":{"file_name":"src/main.rs","byte_start":472,"byte_end":478,"line_start":17,"line_end":17,"column_start":10,"column_end":16},"ref_id":{"krate":2,"index":9364}},{"kind":"Function","span":{"file_name":"src/main.rs","byte_start":441,"byte_end":456,"line_start":16,"line_end":16,"column_start":10,"column_end":25},"ref_id":{"krate":1,"index":5277}},{"kind":"Variable","span":{"file_name":"src/main.rs","byte_start":425,"byte_end":431,"line_start":15,"line_end":15,"column_start":5,"column_end":11},"ref_id":{"krate":0,"index":2952790050}},{"kind":"Function","span":{"file_name":"src/main.rs","byte_start":571,"byte_end":578,"line_start":20,"line_end":20,"column_start":26,"column_end":33},"ref_id":{"krate":1,"index":8118}},{"kind":"Type","span":{"file_name":"src/main.rs","byte_start":581,"byte_end":587,"line_start":20,"line_end":20,"column_start":36,"column_end":42},"ref_id":{"krate":5,"index":8056}},{"kind":"Mod","span":{"file_name":"src/main.rs","byte_start":565,"byte_end":569,"line_start":20,"line_end":20,"column_start":20,"column_end":24},"ref_id":{"krate":1,"index":7483}},{"kind":"Function","span":{"file_name":"src/main.rs","byte_start":655,"byte_end":660,"line_start":23,"line_end":23,"column_start":13,"column_end":18},"ref_id":{"krate":1,"index":984}},{"kind":"Mod","span":{"file_name":"src/main.rs","byte_start":647,"byte_end":653,"line_start":23,"line_end":23,"column_start":5,"column_end":11},"ref_id":{"krate":1,"index":610}},{"kind":"Variable","span":{"file_name":"src/main.rs","byte_start":727,"byte_end":735,"line_start":25,"line_end":25,"column_start":32,"column_end":40},"ref_id":{"krate":0,"index":33}},{"kind":"Function","span":{"file_name":"src/main.rs","byte_start":788,"byte_end":798,"line_start":27,"line_end":27,"column_start":22,"column_end":32},"ref_id":{"krate":1,"index":4516}},{"kind":"Variable","span":{"file_name":"src/main.rs","byte_start":781,"byte_end":787,"line_start":27,"line_end":27,"column_start":15,"column_end":21},"ref_id":{"krate":0,"index":2952790050}},{"kind":"Variable","span":{"file_name":"src/main.rs","byte_start":804,"byte_end":808,"line_start":27,"line_end":27,"column_start":38,"column_end":42},"ref_id":{"krate":0,"index":4093640738}},{"kind":"Type","span":{"file_name":"src/main.rs","byte_start":847,"byte_end":849,"line_start":29,"line_end":29,"column_start":13,"column_end":15},"ref_id":{"krate":2,"index":47178}},{"kind":"Type","span":{"file_name":"src/main.rs","byte_start":847,"byte_end":849,"line_start":29,"line_end":29,"column_start":13,"column_end":15},"ref_id":{"krate":2,"index":47178}},{"kind":"Function","span":{"file_name":"src/main.rs","byte_start":925,"byte_end":932,"line_start":30,"line_end":30,"column_start":68,"column_end":75},"ref_id":{"krate":2,"index":8350}},{"kind":"Type","span":{"file_name":"src/main.rs","byte_start":935,"byte_end":938,"line_start":30,"line_end":30,"column_start":78,"column_end":81},"ref_id":{"krate":5,"index":7435}},{"kind":"Function","span":{"file_name":"src/main.rs","byte_start":901,"byte_end":911,"line_start":30,"line_end":30,"column_start":44,"column_end":54},"ref_id":{"krate":2,"index":8331}},{"kind":"Function","span":{"file_name":"src/main.rs","byte_start":889,"byte_end":898,"line_start":30,"line_end":30,"column_start":32,"column_end":41},"ref_id":{"krate":2,"index":8101}},{"kind":"Variable","span":{"file_name":"src/main.rs","byte_start":884,"byte_end":888,"line_start":30,"line_end":30,"column_start":27,"column_end":31},"ref_id":{"krate":0,"index":4093640738}},{"kind":"Variable","span":{"file_name":"src/main.rs","byte_start":917,"byte_end":918,"line_start":30,"line_end":30,"column_start":60,"column_end":61},"ref_id":{"krate":0,"index":1644167202}},{"kind":"Variable","span":{"file_name":"src/main.rs","byte_start":992,"byte_end":995,"line_start":31,"line_end":31,"column_start":47,"column_end":50},"ref_id":{"krate":0,"index":2315255842}},{"kind":"Type","span":{"file_name":"src/main.rs","byte_start":1051,"byte_end":1054,"line_start":34,"line_end":34,"column_start":13,"column_end":16},"ref_id":{"krate":2,"index":47181}},{"kind":"Type","span":{"file_name":"src/main.rs","byte_start":1051,"byte_end":1054,"line_start":34,"line_end":34,"column_start":13,"column_end":16},"ref_id":{"krate":2,"index":47181}},{"kind":"Function","span":{"file_name":"src/main.rs","byte_start":1071,"byte_end":1075,"line_start":34,"line_end":34,"column_start":33,"column_end":37},"ref_id":{"krate":1,"index":3981}},{"kind":"Variable","span":{"file_name":"src/main.rs","byte_start":1067,"byte_end":1070,"line_start":34,"line_end":34,"column_start":29,"column_end":32},"ref_id":{"krate":0,"index":3992977442}},{"kind":"Type","span":{"file_name":"src/main.rs","byte_start":1092,"byte_end":1102,"line_start":34,"line_end":34,"column_start":54,"column_end":64},"ref_id":{"krate":1,"index":10506}},{"kind":"Type","span":{"file_name":"src/main.rs","byte_start":1081,"byte_end":1090,"line_start":34,"line_end":34,"column_start":43,"column_end":52},"ref_id":{"krate":1,"index":10479}},{"kind":"Type","span":{"file_name":"src/main.rs","byte_start":1122,"byte_end":1125,"line_start":35,"line_end":35,"column_start":13,"column_end":16},"ref_id":{"krate":2,"index":47181}},{"kind":"Type","span":{"file_name":"src/main.rs","byte_start":1122,"byte_end":1125,"line_start":35,"line_end":35,"column_start":13,"column_end":16},"ref_id":{"krate":2,"index":47181}},{"kind":"Function","span":{"file_name":"src/main.rs","byte_start":1262,"byte_end":1270,"line_start":41,"line_end":41,"column_start":18,"column_end":26},"ref_id":{"krate":1,"index":8152}},{"kind":"Variable","span":{"file_name":"src/main.rs","byte_start":1259,"byte_end":1261,"line_start":41,"line_end":41,"column_start":15,"column_end":17},"ref_id":{"krate":0,"index":67108898}},{"kind":"Type","span":{"file_name":"src/main.rs","byte_start":1287,"byte_end":1289,"line_start":42,"line_end":42,"column_start":13,"column_end":15},"ref_id":{"krate":2,"index":47178}},{"kind":"Type","span":{"file_name":"src/main.rs","byte_start":1287,"byte_end":1289,"line_start":42,"line_end":42,"column_start":13,"column_end":15},"ref_id":{"krate":2,"index":47178}},{"kind":"Function","span":{"file_name":"src/main.rs","byte_start":1343,"byte_end":1353,"line_start":43,"line_end":43,"column_start":44,"column_end":54},"ref_id":{"krate":5,"index":5894}},{"kind":"Function","span":{"file_name":"src/main.rs","byte_start":1335,"byte_end":1340,"line_start":43,"line_end":43,"column_start":36,"column_end":41},"ref_id":{"krate":2,"index":2791}},{"kind":"Variable","span":{"file_name":"src/main.rs","byte_start":1331,"byte_end":1334,"line_start":43,"line_end":43,"column_start":32,"column_end":35},"ref_id":{"krate":0,"index":2499805218}},{"kind":"Function","span":{"file_name":"src/main.rs","byte_start":1378,"byte_end":1384,"line_start":44,"line_end":44,"column_start":22,"column_end":28},"ref_id":{"krate":5,"index":7537}},{"kind":"Variable","span":{"file_name":"src/main.rs","byte_start":1373,"byte_end":1377,"line_start":44,"line_end":44,"column_start":17,"column_end":21},"ref_id":{"krate":0,"index":754974754}},{"kind":"Variable","span":{"file_name":"src/main.rs","byte_start":1385,"byte_end":1393,"line_start":44,"line_end":44,"column_start":29,"column_end":37},"ref_id":{"krate":0,"index":33}},{"kind":"Function","span":{"file_name":"src/main.rs","byte_start":1439,"byte_end":1445,"line_start":45,"line_end":45,"column_start":41,"column_end":47},"ref_id":{"krate":2,"index":9364}},{"kind":"Function","span":{"file_name":"src/main.rs","byte_start":1422,"byte_end":1431,"line_start":45,"line_end":45,"column_start":24,"column_end":33},"ref_id":{"krate":1,"index":4572}},{"kind":"Variable","span":{"file_name":"src/main.rs","byte_start":1415,"byte_end":1421,"line_start":45,"line_end":45,"column_start":17,"column_end":23},"ref_id":{"krate":0,"index":2952790050}},{"kind":"Variable","span":{"file_name":"src/main.rs","byte_start":1433,"byte_end":1437,"line_start":45,"line_end":45,"column_start":35,"column_end":39},"ref_id":{"krate":0,"index":754974754}},{"kind":"Variable","span":{"file_name":"src/main.rs","byte_start":1521,"byte_end":1524,"line_start":46,"line_end":46,"column_start":47,"column_end":50},"ref_id":{"krate":0,"index":2499805218}},{"kind":"Type","span":{"file_name":"src/main.rs","byte_start":1553,"byte_end":1556,"line_start":48,"line_end":48,"column_start":13,"column_end":16},"ref_id":{"krate":2,"index":47181}},{"kind":"Type","span":{"file_name":"src/main.rs","byte_start":1571,"byte_end":1576,"line_start":48,"line_end":48,"column_start":31,"column_end":36},"ref_id":{"krate":1,"index":11617}},{"kind":"Type","span":{"file_name":"src/main.rs","byte_start":1557,"byte_end":1569,"line_start":48,"line_end":48,"column_start":17,"column_end":29},"ref_id":{"krate":1,"index":11616}},{"kind":"Type","span":{"file_name":"src/main.rs","byte_start":1553,"byte_end":1556,"line_start":48,"line_end":48,"column_start":13,"column_end":16},"ref_id":{"krate":2,"index":47181}},{"kind":"Type","span":{"file_name":"src/main.rs","byte_start":1571,"byte_end":1576,"line_start":48,"line_end":48,"column_start":31,"column_end":36},"ref_id":{"krate":1,"index":11617}},{"kind":"Type","span":{"file_name":"src/main.rs","byte_start":1557,"byte_end":1569,"line_start":48,"line_end":48,"column_start":17,"column_end":29},"ref_id":{"krate":1,"index":11616}},{"kind":"Type","span":{"file_name":"src/main.rs","byte_start":1597,"byte_end":1600,"line_start":49,"line_end":49,"column_start":13,"column_end":16},"ref_id":{"krate":2,"index":47181}},{"kind":"Type","span":{"file_name":"src/main.rs","byte_start":1615,"byte_end":1627,"line_start":49,"line_end":49,"column_start":31,"column_end":43},"ref_id":{"krate":1,"index":11619}},{"kind":"Type","span":{"file_name":"src/main.rs","byte_start":1601,"byte_end":1613,"line_start":49,"line_end":49,"column_start":17,"column_end":29},"ref_id":{"krate":1,"index":11616}},{"kind":"Type","span":{"file_name":"src/main.rs","byte_start":1597,"byte_end":1600,"line_start":49,"line_end":49,"column_start":13,"column_end":16},"ref_id":{"krate":2,"index":47181}},{"kind":"Type","span":{"file_name":"src/main.rs","byte_start":1615,"byte_end":1627,"line_start":49,"line_end":49,"column_start":31,"column_end":43},"ref_id":{"krate":1,"index":11619}},{"kind":"Type","span":{"file_name":"src/main.rs","byte_start":1601,"byte_end":1613,"line_start":49,"line_end":49,"column_start":17,"column_end":29},"ref_id":{"krate":1,"index":11616}},{"kind":"Function","span":{"file_name":"src/main.rs","byte_start":1665,"byte_end":1670,"line_start":51,"line_end":51,"column_start":17,"column_end":22},"ref_id":{"krate":1,"index":991}},{"kind":"Mod","span":{"file_name":"src/main.rs","byte_start":1657,"byte_end":1663,"line_start":51,"line_end":51,"column_start":9,"column_end":15},"ref_id":{"krate":1,"index":610}},{"kind":"Function","span":{"file_name":"src/main.rs","byte_start":1681,"byte_end":1692,"line_start":51,"line_end":51,"column_start":33,"column_end":44},"ref_id":{"krate":2,"index":13267}},{"kind":"Type","span":{"file_name":"src/main.rs","byte_start":1671,"byte_end":1679,"line_start":51,"line_end":51,"column_start":23,"column_end":31},"ref_id":{"krate":2,"index":49814}},{"kind":"Function","span":{"file_name":"src/main.rs","byte_start":1784,"byte_end":1787,"line_start":56,"line_end":56,"column_start":32,"column_end":35},"ref_id":{"krate":5,"index":5883}},{"kind":"Type","span":{"file_name":"src/main.rs","byte_start":1776,"byte_end":1782,"line_start":56,"line_end":56,"column_start":24,"column_end":30},"ref_id":{"krate":5,"index":8056}},{"kind":"Function","span":{"file_name":"src/main.rs","byte_start":1858,"byte_end":1864,"line_start":59,"line_end":59,"column_start":14,"column_end":20},"ref_id":{"krate":2,"index":9364}},{"kind":"Function","span":{"file_name":"src/main.rs","byte_start":1824,"byte_end":1833,"line_start":58,"line_end":58,"column_start":14,"column_end":23},"ref_id":{"krate":1,"index":4289}},{"kind":"Function","span":{"file_name":"src/main.rs","byte_start":1803,"byte_end":1808,"line_start":57,"line_end":57,"column_start":13,"column_end":18},"ref_id":{"krate":1,"index":4283}},{"kind":"Mod","span":{"file_name":"src/main.rs","byte_start":1799,"byte_end":1801,"line_start":57,"line_end":57,"column_start":9,"column_end":11},"ref_id":{"krate":1,"index":3261}},{"kind":"Variable","span":{"file_name":"src/main.rs","byte_start":1839,"byte_end":1843,"line_start":58,"line_end":58,"column_start":29,"column_end":33},"ref_id":{"krate":0,"index":343932962}},{"kind":"Function","span":{"file_name":"src/main.rs","byte_start":1925,"byte_end":1934,"line_start":60,"line_end":60,"column_start":31,"column_end":40},"ref_id":{"krate":5,"index":6078}},{"kind":"Function","span":{"file_name":"src/main.rs","byte_start":1918,"byte_end":1922,"line_start":60,"line_end":60,"column_start":24,"column_end":28},"ref_id":{"krate":2,"index":13176}},{"kind":"Variable","span":{"file_name":"src/main.rs","byte_start":1913,"byte_end":1917,"line_start":60,"line_end":60,"column_start":19,"column_end":23},"ref_id":{"krate":0,"index":343932962}},{"kind":"Variable","span":{"file_name":"src/main.rs","byte_start":1949,"byte_end":1952,"line_start":61,"line_end":61,"column_start":12,"column_end":15},"ref_id":{"krate":0,"index":2088763426}},{"kind":"Function","span":{"file_name":"src/main.rs","byte_start":1980,"byte_end":1986,"line_start":61,"line_end":61,"column_start":43,"column_end":49},"ref_id":{"krate":2,"index":9334}},{"kind":"Function","span":{"file_name":"src/main.rs","byte_start":1970,"byte_end":1974,"line_start":61,"line_end":61,"column_start":33,"column_end":37},"ref_id":{"krate":1,"index":8125}},{"kind":"Variable","span":{"file_name":"src/main.rs","byte_start":1967,"byte_end":1969,"line_start":61,"line_end":61,"column_start":30,"column_end":32},"ref_id":{"krate":0,"index":4160749602}},{"kind":"Variable","span":{"file_name":"src/main.rs","byte_start":1975,"byte_end":1978,"line_start":61,"line_end":61,"column_start":38,"column_end":41},"ref_id":{"krate":0,"index":2088763426}}],"macro_refs":[],"relations":[]}